.gitignore
README
setup.cfg
setup.py
couchutil/__init__.py
couchutil/changes.py
couchutil/reservation.py
couchutil.egg-info/PKG-INFO
couchutil.egg-info/SOURCES.txt
couchutil.egg-info/dependency_links.txt
couchutil.egg-info/entry_points.txt
couchutil.egg-info/not-zip-safe
couchutil.egg-info/top_level.txt