Metadata-Version: 1.0
Name: couchutil
Version: 0.1.1dev
Summary: utils for couchdb. changes handler and reservation handling ctx mgr.
Home-page: http://ish.io
Author: Tim Parkin & Matt Goodall
Author-email: info@timparkin.co.uk
License: UNKNOWN
Platform: UNKNOWN
